biosimulators_rbapy/__init__.py
biosimulators_rbapy/__main__.py
biosimulators_rbapy/_version.py
biosimulators_rbapy/core.py
biosimulators_rbapy-0.0.4.dist-info/LICENSE
biosimulators_rbapy-0.0.4.dist-info/METADATA
biosimulators_rbapy-0.0.4.dist-info/WHEEL
biosimulators_rbapy-0.0.4.dist-info/entry_points.txt
biosimulators_rbapy-0.0.4.dist-info/top_level.txt
biosimulators_rbapy-0.0.4.dist-info/RECORD
