Metadata-Version: 2.1
Name: biosimulators-rbapy
Version: 0.0.4
Summary: BioSimulators-compliant command-line interface to the RBApy simulation program.
Home-page: https://github.com/biosimulators/Biosimulators_RBApy
Author: BioSimulators Team
Author-email: info@biosimulators.org
License: MIT
Download-URL: https://github.com/biosimulators/Biosimulators_RBApy
Keywords: reaction network,systems biology,computational biology,numerical simulation,resource balance analysis,RBA,BioSimulators,SBML,SED-ML,COMBINE,OMEX,RBApy
Platform: UNKNOWN
Classifier: Development Status :: 3 - Alpha
Classifier: Intended Audience :: Science/Research
Classifier: License :: OSI Approved :: MIT License
Classifier: Topic :: Scientific/Engineering :: Bio-Informatics
License-File: LICENSE
Requires-Dist: biosimulators-utils[logging] (>=0.1.117)
Requires-Dist: kisao (>=2.28)
Requires-Dist: numpy
Provides-Extra: all
Requires-Dist: biosimulators-utils[containers] ; extra == 'all'
Requires-Dist: python-dateutil ; extra == 'all'
Requires-Dist: pyyaml ; extra == 'all'
Requires-Dist: rbapy[cplex] ; extra == 'all'
Requires-Dist: rbapy[glpk] ; extra == 'all'
Requires-Dist: rbapy[gurobi] ; extra == 'all'
Provides-Extra: cplex
Requires-Dist: rbapy[cplex] ; extra == 'cplex'
Provides-Extra: docs
Provides-Extra: glpk
Requires-Dist: rbapy[glpk] ; extra == 'glpk'
Provides-Extra: gurobi
Requires-Dist: rbapy[gurobi] ; extra == 'gurobi'
Provides-Extra: tests
Requires-Dist: biosimulators-utils[containers] ; extra == 'tests'
Requires-Dist: python-dateutil ; extra == 'tests'
Requires-Dist: pyyaml ; extra == 'tests'
